ptcomdo/__init__.py
ptcomdo/api.py
ptcomdo/middleware.py
ptcomdo/response.py
ptcomdo-0.0.2.dist-info/METADATA
ptcomdo-0.0.2.dist-info/WHEEL
ptcomdo-0.0.2.dist-info/top_level.txt
ptcomdo-0.0.2.dist-info/RECORD
