Metadata-Version: 2.1
Name: ptcomdo
Version: 0.0.2
Summary: ptcomdo Python Web Framework built for learning purposes.
Home-page: UNKNOWN
Author: Patrick Walukagga
Author-email: pwalukagga@gmail.com
License: MIT
Platform: UNKNOWN
Classifier: Programming Language :: Python :: 3.7
Requires-Python: >=3.7.0
Requires-Dist: Jinja2 (==2.11.1)
Requires-Dist: parse (==1.15.0)
Requires-Dist: requests (==2.23.0)
Requires-Dist: requests-wsgi-adapter (==0.4.1)
Requires-Dist: WebOb (==1.8.6)
Requires-Dist: whitenoise (==5.0.1)
